irispy/__init__.py
irispy/_version.py
irispy/conftest.py
irispy/meta.py
irispy/obsid.py
irispy/sji.py
irispy/spectrograph.py
irispy/version.py
irispy/visualization.py
irispy/data/README.rst
irispy/data/__init__.py
irispy/data/_sample.py
irispy/data/iris_sra_c_20231106.geny
irispy/data/sample.py
irispy/data/v34-table10.csv
irispy/data/v34-table2000.csv
irispy/data/v36-table10.csv
irispy/data/v36-table2000.csv
irispy/data/v38-table10.csv
irispy/data/v38-table2000.csv
irispy/data/v40-table10.csv
irispy/data/v40-table2000.csv
irispy/data/test/__init__.py
irispy/data/test/compress.py
irispy/data/test/fit_iris_xput_input.sav
irispy/data/test/fit_iris_xput_output.sav
irispy/data/test/get_cali_test_data.pro
irispy/data/test/input_calibration.sav
irispy/data/test/iris_response_2025_08_05T22_25_04_723.sav
irispy/data/test/iris_sra_c_20161022.geny
irispy/data/test/output_calibration.sav
irispy/data/test/raster/iris_l2_20140329_140938_3860258481_SJI_1400_t000.fits
irispy/data/test/raster/iris_l2_20140329_140938_3860258481_SJI_2796_t000_deconvolved.fits
irispy/data/test/raster/iris_l2_20140329_140938_3860258481_SJI_2832_t000.fits
irispy/data/test/raster/iris_l2_20210905_001833_3620258102_raster_t000_r00000.fits
irispy/data/test/raster/overview.txt
irispy/data/test/raster/iris_l2_20140329_140938_3860258481_raster/iris_l2_20140329_140938_3860258481_raster_t000_r00000.fits
irispy/data/test/raster/iris_l2_20140329_140938_3860258481_raster/iris_l2_20140329_140938_3860258481_raster_t000_r00001.fits
irispy/data/test/raster/iris_l2_20140329_140938_3860258481_raster/iris_l2_20140329_140938_3860258481_raster_t000_r00002.fits
irispy/data/test/raster/iris_l2_20140329_140938_3860258481_raster/iris_l2_20140329_140938_3860258481_raster_t000_r00003.fits
irispy/data/test/raster/iris_l2_20140329_140938_3860258481_raster/iris_l2_20140329_140938_3860258481_raster_t000_r00004.fits
irispy_lmsal-0.5.0.dist-info/licenses/licenses/LICENSE.rst
irispy_lmsal-0.5.0.dist-info/METADATA
irispy_lmsal-0.5.0.dist-info/WHEEL
irispy_lmsal-0.5.0.dist-info/top_level.txt
irispy_lmsal-0.5.0.dist-info/RECORD
